nodzz/__init__.py
nodzz/basic_types.py
nodzz/config.py
nodzz/core.py
nodzz/tree.py
nodzz/utils.py
nodzz/async_nodes/__init__.py
nodzz/async_nodes/base.py
nodzz/async_nodes/controllers.py
nodzz/nodes/__init__.py
nodzz/nodes/base.py
nodzz/nodes/controllers.py
nodzz/nodes/tasks.py
nodzz-0.2.0.dist-info/LICENSE
nodzz-0.2.0.dist-info/METADATA
nodzz-0.2.0.dist-info/WHEEL
nodzz-0.2.0.dist-info/top_level.txt
nodzz-0.2.0.dist-info/RECORD
