Metadata-Version: 2.1
Name: nodzz
Version: 0.2.0
Summary: Pure Python behavior trees framework
Home-page: https://github.com/duskforge/nodzz
Author: Dusk Forge
Author-email: duskforge@protonmail.com
License: UNKNOWN
Project-URL: Bug Tracker, https://github.com/duskforge/nodzz/issues
Platform: UNKNOWN
Classifier: Development Status :: 3 - Alpha
Classifier: Environment :: Console
Classifier: Programming Language :: Python :: 3
Classifier: Programming Language :: Python :: 3 :: Only
Classifier: Programming Language :: Python :: 3.8
Classifier: Programming Language :: Python :: 3.9
Classifier: Programming Language :: Python :: 3.10
Classifier: License :: OSI Approved :: MIT License
Classifier: Operating System :: OS Independent
Classifier: Topic :: Scientific/Engineering :: Artificial Intelligence
Classifier: Topic :: Software Development :: Libraries :: Python Modules
Requires-Python: >=3.8
License-File: LICENSE
Requires-Dist: pydantic (>=1.8.2)
Requires-Dist: pyyaml (>=5.4.1)
